adss/__init__.py
adss/auth.py
adss/client.py
adss/exceptions.py
adss/utils.py
adss/endpoints/__init__.py
adss/endpoints/admin.py
adss/endpoints/images.py
adss/endpoints/metadata.py
adss/endpoints/queries.py
adss/endpoints/users.py
adss/models/__init__.py
adss/models/metadata.py
adss/models/query.py
adss/models/user.py
adss-1.35.dist-info/licenses/LICENSE
dev/fetch_idr6.py
dev/natnael.py
adss-1.35.dist-info/METADATA
adss-1.35.dist-info/WHEEL
adss-1.35.dist-info/top_level.txt
adss-1.35.dist-info/RECORD
