Metadata-Version: 2.4
Name: adss
Version: 1.35
Summary: Astronomical Data Smart System
Author-email: Gustavo Schwarz <gustavo.b.schwarz@gmail.com>
Project-URL: Homepage, https://github.com/schwarzam/adss
Classifier: Programming Language :: Python :: 3
Requires-Python: >=3.8
License-File: LICENSE
Requires-Dist: pyarrow
Requires-Dist: httpx
Requires-Dist: requests
Requires-Dist: astropy
Dynamic: license-file
